pycertmanager/__init__.py
pycertmanager/exceptions.py
pycertmanager-0.0.6.dist-info/LICENSE
pycertmanager-0.0.6.dist-info/METADATA
pycertmanager-0.0.6.dist-info/WHEEL
pycertmanager-0.0.6.dist-info/top_level.txt
pycertmanager-0.0.6.dist-info/RECORD
