Metadata-Version: 2.1
Name: pycertmanager
Version: 0.0.6
Summary: Module to assist in the programmatic management of PFX digital certificates
Author-email: Elder Santos <elder_rn@hotmail.com>
License: MIT
Project-URL: Homepage, https://github.com/eldersantoss/pycertmanager
Project-URL: Bug Tracker, https://github.com/eldersantoss/pycertmanager/issues
Classifier: License :: OSI Approved :: MIT License
Classifier: Programming Language :: Python :: 3
Classifier: Topic :: Security
Requires-Python: >=3.10
License-File: LICENSE
Requires-Dist: cryptography (>=38.0.1)
Provides-Extra: build
Requires-Dist: build ; extra == 'build'
Requires-Dist: twine ; extra == 'build'
Provides-Extra: dev
Requires-Dist: black ; extra == 'dev'
Requires-Dist: bumpver ; extra == 'dev'
Requires-Dist: coverage ; extra == 'dev'
